{
  "type": "sas:shaped_wand",
  "group": "wands",
  "key": {
    "B": {
      "item": "minecraft:fire_charge"
    },
    "C": {
      "type": "forge:nbt",
      "count": 1,
      "item": "sas:wand_core",
      "nbt": "{ability:\"sas:large_fireball\"}"
    },
    "L": {
      "tag": "forge:leather"
    },
    "S": {
      "item": "sas:handle"
    }
  },
  "pattern": [
    "BCB",
    "LSL"
  ],
  "result": {
    "type": "sas:wand_ability",
    "ability": {
      "children": [],
      "id": "sas:large_fireball"
    },
    "item": "sas:wand",
    "powered_up": false
  }
}